{
  "id": "sfsg-temple-united-methodist-church-3",
  "name": "Temple United Methodist Church",
  "category": "sfserviceguide",
  "description": "Temple UMC runs a food pantry every Wednesday",
  "fullDescription": "Temple UMC runs a food pantry every Wednesday",
  "whatTheyOffer": "Temple United Methodist Church is a diverse Christian community of people who are committed to Jesus Christ, to one another, and to offering God's healing love in San Francisco and throughout the world. Service is live-streamed on their YouTube channel @TUMCpeace at 10 AM on Sunday mornings.",
  "howToGetIt": null,
  "groups": [
    "everyone"
  ],
  "areas": [
    "San Francisco"
  ],
  "city": "San Francisco",
  "website": "",
  "cost": null,
  "phone": "4155861444",
  "email": "info@tumcpeace.org",
  "address": "65 Beverly Street, San Francisco, CA, 94132",
  "requirements": null,
  "howToApply": null,
  "keywords": [
    "san francisco",
    "sf service guide",
    "food"
  ],
  "lifeEvents": [],
  "agency": null,
  "lastUpdated": "2026-01-22",
  "dataSource": "dataSF",
  "externalId": "3",
  "sourceUrl": "https://www.sfserviceguide.org/services/3"
}