{
  "id": "sfsg-collective-impact-995",
  "name": "Collective Impact",
  "category": "sfserviceguide",
  "description": "Collective Impact's mission is to provide youth, families, and programs the tools and resources they need to succeed.",
  "fullDescription": "Collective Impact's mission is to provide youth, families, and programs the tools and resources they need to succeed.",
  "whatTheyOffer": "Ella Hill Hutch Community Center opened its doors to the Western Addition area of San Francisco over 30 years ago. A full-service site, the center boasts a gymnasium, playground, community gardens, classroom space, a computer lab, and four newly resurfaced tennis courts. The tennis courts at Ella Hill Hutch Community Center are open to the public Mon through Friday; anyone is welcome to reserve time and play on a first-come, first-served basis. In addition to being available to the general publi",
  "howToGetIt": null,
  "groups": [
    "everyone"
  ],
  "areas": [
    "San Francisco"
  ],
  "city": "​San Francisco",
  "website": "",
  "cost": null,
  "phone": "4155670400",
  "email": "info@collectiveimpact.org",
  "address": "699 Hayes Street, ,  ​San Francisco, CA, 94102",
  "requirements": null,
  "howToApply": null,
  "keywords": [
    "san francisco",
    "sf service guide"
  ],
  "lifeEvents": [],
  "agency": null,
  "lastUpdated": "2026-01-22",
  "dataSource": "dataSF",
  "externalId": "995",
  "sourceUrl": "https://www.sfserviceguide.org/services/995"
}