{
  "id": "sfsg-education-5113",
  "name": "Education",
  "category": "sfserviceguide",
  "description": "School Type: Elementary School Serves Grades: TK, K, 1, 2, 3, 4, 5",
  "fullDescription": "School Type: Elementary School Serves Grades: TK, K, 1, 2, 3, 4, 5",
  "whatTheyOffer": "School Type: Elementary School Serves Grades: TK, K, 1, 2, 3, 4, 5",
  "howToGetIt": "How to Enroll: Enrollment Requirements and Instructions",
  "groups": [
    "everyone"
  ],
  "areas": [
    "San Francisco"
  ],
  "city": "San Francisco",
  "website": "https://www.sfusd.edu/school/longfellow-elementary-school",
  "cost": null,
  "phone": "4154694730",
  "email": null,
  "address": "755 Morse Street, San Francisco, CA, 94112",
  "requirements": null,
  "howToApply": null,
  "keywords": [
    "san francisco",
    "sf service guide",
    "education",
    "stem",
    "academic support",
    "public schools"
  ],
  "lifeEvents": [],
  "agency": "Longfellow Elementary",
  "lastUpdated": "2026-01-22",
  "dataSource": "dataSF",
  "externalId": "5113",
  "sourceUrl": "https://www.sfusd.edu/school/longfellow-elementary-school"
}